ayaya/__init__.py
ayaya-0.1.0.dist-info/LICENSE.txt
ayaya-0.1.0.dist-info/METADATA
ayaya-0.1.0.dist-info/WHEEL
ayaya-0.1.0.dist-info/top_level.txt
ayaya-0.1.0.dist-info/RECORD
